{"annotatable":{"parts":["s1p1","s1p2","s1p3","s1p4","s1p5","s1p6","s1p7","s1p8","s1p9","s1p10","s1p11","s1p12","s1p13","s1p14","s1p15","s1p16","s1p17"]},"anncomplete":true,"sources":[],"metas":{},"entities":[{"classId":"e_3","part":"s1p2","offsets":[{"start":0,"text":"تحرير"}],"coordinates":[],"confidence":{"state":"pre-added","who":["user:abdmoh"],"prob":1},"fields":{},"normalizations":{}},{"classId":"e_2","part":"s1p2","offsets":[{"start":6,"text":"مدنيين من سجن ل«طالبان"}],"coordinates":[],"confidence":{"state":"pre-added","who":["user:abdmoh"],"prob":1},"fields":{},"normalizations":{}},{"classId":"e_3","part":"s1p8","offsets":[{"start":0,"text":"حررت"}],"coordinates":[],"confidence":{"state":"pre-added","who":["user:abdmoh"],"prob":1},"fields":{},"normalizations":{}},{"classId":"e_1","part":"s1p8","offsets":[{"start":5,"text":"القوات الخاصة الأفغانية"}],"coordinates":[],"confidence":{"state":"pre-added","who":["user:abdmoh"],"prob":1},"fields":{},"normalizations":{}},{"classId":"e_2","part":"s1p8","offsets":[{"start":32,"text":"مدنياً"}],"coordinates":[],"confidence":{"state":"pre-added","who":["user:abdmoh"],"prob":1},"fields":{},"normalizations":{}},{"classId":"e_8","part":"s1p8","offsets":[{"start":73,"text":"إقليم هلمند"}],"coordinates":[],"confidence":{"state":"pre-added","who":["user:abdmoh"],"prob":1},"fields":{},"normalizations":{}},{"classId":"e_2","part":"s1p8","offsets":[{"start":123,"text":"مدنيين"}],"coordinates":[],"confidence":{"state":"pre-added","who":["ml:regex"],"prob":0},"fields":{},"normalizations":{}},{"classId":"e_3","part":"s1p8","offsets":[{"start":130,"text":"حتفهم"}],"coordinates":[],"confidence":{"state":"pre-added","who":["user:abdmoh"],"prob":1},"fields":{},"normalizations":{}},{"classId":"e_3","part":"s1p8","offsets":[{"start":149,"text":"انفجار"}],"coordinates":[],"confidence":{"state":"pre-added","who":["user:abdmoh"],"prob":1},"fields":{},"normalizations":{}},{"classId":"e_2","part":"s1p8","offsets":[{"start":171,"text":"إقليم هيرات"}],"coordinates":[],"confidence":{"state":"pre-added","who":["user:abdmoh"],"prob":1},"fields":{},"normalizations":{}},{"classId":"e_2","part":"s1p8","offsets":[{"start":264,"text":"مدنيين"}],"coordinates":[],"confidence":{"state":"pre-added","who":["ml:regex"],"prob":0},"fields":{},"normalizations":{}},{"classId":"e_3","part":"s1p8","offsets":[{"start":271,"text":"احتجزوا"}],"coordinates":[],"confidence":{"state":"pre-added","who":["user:abdmoh"],"prob":1},"fields":{},"normalizations":{}},{"classId":"e_7","part":"s1p8","offsets":[{"start":303,"text":"منطقة سانجين"}],"coordinates":[],"confidence":{"state":"pre-added","who":["user:abdmoh"],"prob":1},"fields":{},"normalizations":{}},{"classId":"e_9","part":"s1p8","offsets":[{"start":322,"text":"مزاعم عن تعاونهم"}],"coordinates":[],"confidence":{"state":"pre-added","who":["user:abdmoh"],"prob":1},"fields":{},"normalizations":{}},{"classId":"e_9","part":"s1p8","offsets":[{"start":350,"text":"لم يُقتل"}],"coordinates":[],"confidence":{"state":"pre-added","who":["user:abdmoh"],"prob":1},"fields":{},"normalizations":{}},{"classId":"e_3","part":"s1p8","offsets":[{"start":382,"text":"الإنقاذ"}],"coordinates":[],"confidence":{"state":"pre-added","who":["user:abdmoh"],"prob":1},"fields":{},"normalizations":{}},{"classId":"e_3","part":"s1p9","offsets":[{"start":1,"text":"أفرجت"}],"coordinates":[],"confidence":{"state":"pre-added","who":["user:abdmoh"],"prob":1},"fields":{},"normalizations":{}},{"classId":"e_1","part":"s1p9","offsets":[{"start":7,"text":"القوات الخاصة الأفغانية"}],"coordinates":[],"confidence":{"state":"pre-added","who":["ml:regex"],"prob":0},"fields":{},"normalizations":{}},{"classId":"e_2","part":"s1p9","offsets":[{"start":42,"text":"مدنيين"}],"coordinates":[],"confidence":{"state":"pre-added","who":["ml:regex","user:abdmoh"],"prob":1},"fields":{},"normalizations":{}},{"classId":"e_2","part":"s1p9","offsets":[{"start":58,"text":"نساء"}],"coordinates":[],"confidence":{"state":"pre-added","who":["user:abdmoh"],"prob":1},"fields":{},"normalizations":{}},{"classId":"e_2","part":"s1p9","offsets":[{"start":64,"text":"أطفال"}],"coordinates":[],"confidence":{"state":"pre-added","who":["user:abdmoh"],"prob":1},"fields":{},"normalizations":{}},{"classId":"e_3","part":"s1p10","offsets":[{"start":16,"text":"قُتل"}],"coordinates":[],"confidence":{"state":"pre-added","who":["user:abdmoh"],"prob":1},"fields":{},"normalizations":{}},{"classId":"e_2","part":"s1p10","offsets":[{"start":21,"text":"قيادي من «طالبان»"}],"coordinates":[],"confidence":{"state":"pre-added","who":["user:abdmoh"],"prob":1},"fields":{},"normalizations":{}},{"classId":"e_8","part":"s1p10","offsets":[{"start":40,"text":"إقليم جوزجان"}],"coordinates":[],"confidence":{"state":"pre-added","who":["user:abdmoh"],"prob":1},"fields":{},"normalizations":{}},{"classId":"e_3","part":"s1p10","offsets":[{"start":68,"text":"عملية جوية"}],"coordinates":[],"confidence":{"state":"pre-added","who":["user:abdmoh"],"prob":1},"fields":{},"normalizations":{}},{"classId":"e_3","part":"s1p10","offsets":[{"start":81,"text":"أصيب"}],"coordinates":[],"confidence":{"state":"pre-added","who":["user:abdmoh"],"prob":1},"fields":{},"normalizations":{}},{"classId":"e_2","part":"s1p10","offsets":[{"start":95,"text":"أعوانه"}],"coordinates":[],"confidence":{"state":"pre-added","who":["user:abdmoh"],"prob":1},"fields":{},"normalizations":{}},{"classId":"e_3","part":"s1p10","offsets":[{"start":105,"text":"القصف الجوي"}],"coordinates":[],"confidence":{"state":"pre-added","who":["user:abdmoh"],"prob":1},"fields":{},"normalizations":{}},{"classId":"e_7","part":"s1p10","offsets":[{"start":118,"text":"منطقة فايز آباد"}],"coordinates":[],"confidence":{"state":"pre-added","who":["user:abdmoh"],"prob":1},"fields":{},"normalizations":{}}],"relations":[{"classId":"r_4","type":"linked","directed":false,"entities":["s1p8|e_1|5,27","s1p8|e_3|0,3"],"confidence":{"state":"pre-added","who":["user:abdmoh"],"prob":1}},{"classId":"r_4","type":"linked","directed":false,"entities":["s1p9|e_3|1,5","s1p9|e_1|7,29"],"confidence":{"state":"pre-added","who":["user:abdmoh"],"prob":1}},{"classId":"r_5","type":"linked","directed":false,"entities":["s1p2|e_2|6,27","s1p2|e_3|0,4"],"confidence":{"state":"pre-added","who":["user:abdmoh"],"prob":1}},{"classId":"r_5","type":"linked","directed":false,"entities":["s1p8|e_2|32,37","s1p8|e_3|0,3"],"confidence":{"state":"pre-added","who":["user:abdmoh"],"prob":1}},{"classId":"r_5","type":"linked","directed":false,"entities":["s1p8|e_3|130,134","s1p8|e_2|123,128"],"confidence":{"state":"pre-added","who":["user:abdmoh"],"prob":1}},{"classId":"r_5","type":"linked","directed":false,"entities":["s1p8|e_3|149,154","s1p8|e_2|123,128"],"confidence":{"state":"pre-added","who":["user:abdmoh"],"prob":1}},{"classId":"r_5","type":"linked","directed":false,"entities":["s1p8|e_3|271,277","s1p8|e_2|264,269"],"confidence":{"state":"pre-added","who":["user:abdmoh"],"prob":1}},{"classId":"r_5","type":"linked","directed":false,"entities":["s1p9|e_2|42,47","s1p9|e_3|1,5"],"confidence":{"state":"pre-added","who":["user:abdmoh"],"prob":1}},{"classId":"r_5","type":"linked","directed":false,"entities":["s1p9|e_2|58,61","s1p9|e_3|1,5"],"confidence":{"state":"pre-added","who":["user:abdmoh"],"prob":1}},{"classId":"r_5","type":"linked","directed":false,"entities":["s1p9|e_2|64,68","s1p9|e_3|1,5"],"confidence":{"state":"pre-added","who":["user:abdmoh"],"prob":1}},{"classId":"r_5","type":"linked","directed":false,"entities":["s1p10|e_3|16,19","s1p10|e_2|21,37"],"confidence":{"state":"pre-added","who":["user:abdmoh"],"prob":1}},{"classId":"r_5","type":"linked","directed":false,"entities":["s1p10|e_3|68,77","s1p10|e_2|21,37"],"confidence":{"state":"pre-added","who":["user:abdmoh"],"prob":1}},{"classId":"r_5","type":"linked","directed":false,"entities":["s1p10|e_2|95,100","s1p10|e_3|81,84"],"confidence":{"state":"pre-added","who":["user:abdmoh"],"prob":1}}]}